README.md
setup.py
dumb_menu/__init__.py
dumb_menu_lw.egg-info/PKG-INFO
dumb_menu_lw.egg-info/SOURCES.txt
dumb_menu_lw.egg-info/dependency_links.txt
dumb_menu_lw.egg-info/requires.txt
dumb_menu_lw.egg-info/top_level.txt